struphy/__init__.py
struphy/compile_struphy.mk
struphy/conftest.py
struphy/dependencies.py
struphy/main.py
struphy/psydac-3.0.0.dev0-py3-none-any.whl
struphy/bsplines/__init__.py
struphy/bsplines/bsplines.py
struphy/bsplines/bsplines_kernels.py
struphy/bsplines/evaluation_kernels_1d.py
struphy/bsplines/evaluation_kernels_2d.py
struphy/bsplines/evaluation_kernels_3d.py
struphy/bsplines/shapefunc_kernels.py
struphy/bsplines/tests/__init__.py
struphy/bsplines/tests/test_bsplines_kernels.py
struphy/bsplines/tests/test_eval_spline_mpi.py
struphy/console/__init__.py
struphy/console/compile.py
struphy/console/format.py
struphy/console/likwid.py
struphy/console/main.py
struphy/console/params.py
struphy/console/parsers.py
struphy/console/profile.py
struphy/console/test.py
struphy/console/tests/test_console.py
struphy/diagnostics/__init__.py
struphy/diagnostics/console_diagn.py
struphy/diagnostics/continuous_spectra.py
struphy/diagnostics/diagn_tools.py
struphy/diagnostics/paraview/__init__.py
struphy/diagnostics/paraview/mesh_creator.py
struphy/diagnostics/paraview/vtk_writer.py
struphy/dispersion_relations/__init__.py
struphy/dispersion_relations/analytic.py
struphy/dispersion_relations/base.py
struphy/dispersion_relations/utilities.py
struphy/eigenvalue_solvers/__init__.py
struphy/eigenvalue_solvers/derivatives.py
struphy/eigenvalue_solvers/kernels_2d.py
struphy/eigenvalue_solvers/kernels_3d.py
struphy/eigenvalue_solvers/kernels_projectors_global.py
struphy/eigenvalue_solvers/kernels_projectors_global_mhd.py
struphy/eigenvalue_solvers/mass_matrices_1d.py
struphy/eigenvalue_solvers/mass_matrices_2d.py
struphy/eigenvalue_solvers/mass_matrices_3d.py
struphy/eigenvalue_solvers/mhd_axisymmetric_main.py
struphy/eigenvalue_solvers/mhd_axisymmetric_pproc.py
struphy/eigenvalue_solvers/mhd_operators.py
struphy/eigenvalue_solvers/mhd_operators_core.py
struphy/eigenvalue_solvers/projectors_global.py
struphy/eigenvalue_solvers/spline_space.py
struphy-3.0.0.dist-info/licenses/LICENSE
struphy-3.0.0.dist-info/METADATA
struphy-3.0.0.dist-info/WHEEL
struphy-3.0.0.dist-info/entry_points.txt
struphy-3.0.0.dist-info/top_level.txt
struphy-3.0.0.dist-info/RECORD
