Metadata-Version: 2.4
Name: struphy
Version: 3.0.0
Summary: Multi-model plasma physics package
Author: Max Planck Institute for Plasma Physics
Author-email: stefan.possanner@ipp.mpg.de, max.lindqvist@ipp.mpg.de, eric.sonnendruecker@ipp.mpg.de
License: Copyright (c) 2019-2025, Struphy developers, Max Planck Institute for Plasma Physics
Project-URL: homepage, https://struphy-hub.github.io/struphy/index.html
Project-URL: documentation, https://struphy-hub.github.io/struphy/index.html
Project-URL: repository, https://github.com/struphy-hub/struphy
Project-URL: changelog, https://github.com/struphy-hub/struphy/blob/devel/CHANGELOG.md
Project-URL: Bug Tracker, https://github.com/struphy-hub/struphy/issues
Keywords: plasma physics, fusion, numerical modeling, partial differential equations, energetic particles
Classifier: Programming Language :: Python :: 3
Requires-Python: >=3.10
License-File: LICENSE
Requires-Dist: numpy<=2.2.6
Requires-Dist: cunumpy<=0.1
Requires-Dist: pyccel<=2.0.1,>=2.0
Requires-Dist: scipy<=1.15.3
Requires-Dist: h5py<=3.14.0
Requires-Dist: matplotlib<=3.10.5
Requires-Dist: pyyaml<=6.0.3
Requires-Dist: vtk<=9.5.2
Requires-Dist: tqdm<=4.67.1
Requires-Dist: argcomplete<=3.6.3
Requires-Dist: pytest<=9.0.1
Requires-Dist: pytest-mpi<=0.6
Requires-Dist: line_profiler<=5.0.0
Provides-Extra: phys
Requires-Dist: gvec<=1.2.0,>=1.1.0; extra == "phys"
Requires-Dist: desc-opt<=0.15.0; extra == "phys"
Provides-Extra: dev
Requires-Dist: struphy[mpi]; extra == "dev"
Requires-Dist: notebook<=7.4.7; extra == "dev"
Requires-Dist: autopep8<=2.3.2; extra == "dev"
Requires-Dist: isort<=7.0.0; extra == "dev"
Requires-Dist: flake8<=7.3.0; extra == "dev"
Requires-Dist: pylint<=4.0.2; extra == "dev"
Requires-Dist: ssort<=0.15.0; extra == "dev"
Requires-Dist: add-trailing-comma<=4.0.0; extra == "dev"
Requires-Dist: ruff<=0.14.4,>=0.9.1; extra == "dev"
Requires-Dist: pre-commit<=4.4.0; extra == "dev"
Requires-Dist: nbstripout<=0.8.1; extra == "dev"
Requires-Dist: tabulate<=0.9.0; extra == "dev"
Requires-Dist: tomli-w<=1.2.0; extra == "dev"
Requires-Dist: kaleido<=1.2.0; extra == "dev"
Requires-Dist: pandas<=2.3.3; extra == "dev"
Requires-Dist: plotly<=6.3.0; extra == "dev"
Provides-Extra: mpi
Requires-Dist: mpi4py<=4.1.1; extra == "mpi"
Provides-Extra: doc
Requires-Dist: struphy[phys]; extra == "doc"
Requires-Dist: jupyter<=1.1.1; extra == "doc"
Requires-Dist: nbconvert<=6.5.4; extra == "doc"
Requires-Dist: ipykernel<=7.1.0; extra == "doc"
Requires-Dist: sphinx<=8.1.3; extra == "doc"
Requires-Dist: sphinx-design<=0.6.1; extra == "doc"
Requires-Dist: lxml_html_clean<=0.4.3; extra == "doc"
Requires-Dist: sphinxcontrib-napoleon<=0.7; extra == "doc"
Requires-Dist: sphinx-copybutton<=0.5.2; extra == "doc"
Requires-Dist: pydata-sphinx-theme<=0.16.1; extra == "doc"
Requires-Dist: nbsphinx<=0.9.7; extra == "doc"
Requires-Dist: m2r2<=0.3.4; extra == "doc"
Requires-Dist: myst-parser<=4.0.1; extra == "doc"
Requires-Dist: mistune<=0.8.4; extra == "doc"
Requires-Dist: docutils<=0.21.2; extra == "doc"
Requires-Dist: ipyparallel<=9.0.2; extra == "doc"
Provides-Extra: likwid
Requires-Dist: struphy[dev]; extra == "likwid"
Requires-Dist: pylikwid; extra == "likwid"
Provides-Extra: all
Requires-Dist: struphy[phys]; extra == "all"
Requires-Dist: struphy[dev]; extra == "all"
Requires-Dist: struphy[mpi]; extra == "all"
Requires-Dist: struphy[doc]; extra == "all"
Dynamic: license-file
